Metadata-Version: 2.1
Name: aiogram-autodoc
Version: 0.0.2
Summary: Generates command documentation from handlers
Home-page: https://github.com/viuipan/aiogram-autodoc
Author-email: viuipan@gmail.com
License: MIT
Platform: UNKNOWN
